quackify/__init__.py
quackify/delay.py
quackify/hotkeys.py
quackify/mouse_click.py
quackify/mouse_move.py
quackify/rem.py
quackify/send.py
quackify-1.0.0.dist-info/METADATA
quackify-1.0.0.dist-info/WHEEL
quackify-1.0.0.dist-info/top_level.txt
quackify-1.0.0.dist-info/RECORD
