Metadata-Version: 2.1
Name: quackify
Version: 1.0.0
Summary: Quackify es una biblioteca para Python que emula diversas funciones del duckyscript.
Home-page: https://github.com/Euronymou5/Quackify
Author: Euronymou5
License: Mozilla Public License 2.0
Classifier: License :: OSI Approved :: Mozilla Public License 2.0 (MPL 2.0)
Classifier: Programming Language :: Python :: 3
Classifier: Topic :: Software Development :: Libraries :: Python Modules
Classifier: Operating System :: OS Independent
Requires-Dist: pyautogui
Requires-Dist: pynput
